{
    "question-number": "IV.(A)",
    "question-text": "Write the appropriate words or groups of words to complete the line of verce.",
    "marks": "(5 marks)",
    "set1": [
        {
            "question-item-number": "(1)",
            "question-item-text": [
                "See the moon, a sandy dune,",
                "Or catch ---------- pike."
            ]
        },
        {
            "question-item-number": "(2)",
            "question-item-text": [
                "---------- by night; study and ease,",
                "Together mix’d; sweet recreation."
            ]
        },
        {
            "question-item-number": "(3)",
            "question-item-text": [
                "And both that morning equally lay",
                "In leaves no step ---------- black."
            ]
        },
        {
            "question-item-number": "(4)",
            "question-item-text": [
                "All night long in the dark and wet,",
                "---------- goes riding by."
            ]
        },
        {
            "question-item-number": "(5)",
            "question-item-text": [
                "I shall be telling this with ----------",
                "Somewhere ages and ages hence:"
            ]
        }
    ],
    "set2": [
        {
            "question-item-number": "(1)",
            "question-item-text": [
                "I shall be telling this with a sigh",
                "Somewhere ages and ages ----------:"
            ]
        },
        {
            "question-item-number": "(2)",
            "question-item-text": [
                "Late in the night when the ---------- are out,",
                "Why does he gallop and gallop about?"
            ]
        },
        {
            "question-item-number": "(3)",
            "question-item-text": [
                "And looked down one as far as I could",
                "To where it bent in the ----------;"
            ]
        },
        {
            "question-item-number": "(4)",
            "question-item-text": [
                "See the moon, a sandy dune,",
                "Or catch ---------- pike."
            ]
        },
        {
            "question-item-number": "(5)",
            "question-item-text": [
                "Whose herds with milk, whose fields with bread,",
                "Whose flocks supply him with ----------;"
            ]
        }
    ],
    "set3": [
        {
            "question-item-number": "(1)",
            "question-item-text": [
                "Two roads ---------- in yellow wood,",
                "And sorry I could not travel both"
            ]
        },
        {
            "question-item-number": "(2)",
            "question-item-text": [
                "Blest, who ---------- find",
                "Hours, days, and years slide soft away"
            ]
        },
        {
            "question-item-number": "(3)",
            "question-item-text": [
                "A world is there for you to share",
                "When ---------- calls."
            ]
        },
        {
            "question-item-number": "(4)",
            "question-item-text": [
                "Whenever the trees are crying aloud,",
                "And ships are ---------- at sea"
            ]
        },
        {
            "question-item-number": "(5)",
            "question-item-text": [
                "And both that morning equally lay",
                "In leaves no step had ----------."
            ]
        }
    ],
    "set4": [
        {
            "question-item-number": "(1)",
            "question-item-text": [
                "You cannot tell ----------",
                "By the way the building looks,"
            ]
        },
        {
            "question-item-number": "(2)",
            "question-item-text": [
                "Blest, ---------- unconcern’dly find",
                "Hours, days, and years slide soft away"
            ]
        },
        {
            "question-item-number": "(3)",
            "question-item-text": [
                "Everything ---------- can bring",
                "You’ll find inside those walls"
            ]
        },
        {
            "question-item-number": "(4)",
            "question-item-text": [
                "I shall be telling this with a sigh",
                "---------- and ages hence:"
            ]
        },
        {
            "question-item-number": "(5)",
            "question-item-text": [
                "Whenever the trees are crying aloud,",
                "And ships ---------- at sea,"
            ]
        }
    ]
}